kdslib/__init__.py
kdslib/kdsdatautil.py
kdslib/kdsfunctionalutil.py
kdslib/kdsutil.py
kdslib-1.0.7.dist-info/LICENSE
kdslib-1.0.7.dist-info/METADATA
kdslib-1.0.7.dist-info/WHEEL
kdslib-1.0.7.dist-info/top_level.txt
kdslib-1.0.7.dist-info/RECORD
