Metadata-Version: 2.1
Name: kdslib
Version: 1.0.7
Summary: KDS logging and data connection helpers
Home-page: UNKNOWN
Author: kdslibraries
Author-email: kdslibraries@aol.com
License: UNKNOWN
Keywords: python,kdslib
Platform: UNKNOWN
Classifier: Development Status :: 5 - Production/Stable
Classifier: Intended Audience :: Developers
Classifier: Programming Language :: Python :: 3
Classifier: License :: OSI Approved :: GNU Lesser General Public License v3 or later (LGPLv3+)
Classifier: Operating System :: MacOS :: MacOS X
Classifier: Operating System :: Microsoft :: Windows
Requires-Dist: msal
Requires-Dist: requests
Requires-Dist: sqlalchemy
Requires-Dist: teradata
Requires-Dist: teradatasql
Requires-Dist: pymssql
Requires-Dist: teradatasqlalchemy
